glmtools/__init__.py
glmtools/data.py
glmtools/design.py
glmtools/example.py
glmtools/fit.py
glmtools/io.py
glmtools/permutations.py
glmtools/regressors.py
glmtools/stats.py
glmtools/util.py
glmtools/viz.py
glmtools-0.3.0.dist-info/METADATA
glmtools-0.3.0.dist-info/WHEEL
glmtools-0.3.0.dist-info/top_level.txt
glmtools-0.3.0.dist-info/RECORD
